{"data":[{"title":"关于我","description":"","url":"about/index.html","api":"api/pages/about.json"},{"title":"旅行足迹","description":"","url":"about/travel.html","api":"api/pages/about.json"},{"title":"留言板","description":"","url":"message/index.html","api":"api/pages/message.json"},{"title":"项目详细介绍","description":"Here&#39;s something encrypted, password is required to continue reading.","url":"resume/index.html","api":"api/pages/resume.json"},{"title":"project","description":"","url":"project/index.html","api":"api/pages/project.json"}],"api":"api/pages.json"}